{
  "ProviderId": "Microsoft.VisualStudio.ConnectedService.Wcf",
  "Version": "15.0.20119.1312",
  "GettingStartedDocument": {
    "Uri": "https://go.microsoft.com/fwlink/?linkid=858517"
  },
  "ExtendedData": {
    "Uri": "https://itrinity.utilibill.com.au/itrinity/UtbCustomer?wsdl",
    "Namespace": "wsUtbCustomer",
    "SelectedAccessLevelForGeneratedClass": "Public",
    "GenerateMessageContract": false,
    "ReuseTypesinReferencedAssemblies": false,
    "ReuseTypesinAllReferencedAssemblies": true,
    "CollectionTypeReference": {
      "Item1": "System.Array",
      "Item2": "System.Runtime.dll"
    },
    "DictionaryCollectionTypeReference": {
      "Item1": "System.Collections.Generic.Dictionary`2",
      "Item2": "System.Collections.dll"
    },
    "CheckedReferencedAssemblies": [],
    "InstanceId": null,
    "Name": "wsUtbCustomer",
    "Metadata": {}
  }
}